__init__.py
configAWSEnv/__init__.py
configAWSEnv/config_ec2_env.py
configAWSEnv/connection.py
configAWSEnv/const.py
configAWSEnv/parser.py
configAWSEnv/prints.py
configAWSEnv-0.0.11.data/scripts/configEnv.py
configAWSEnv-0.0.11.dist-info/DESCRIPTION.rst
configAWSEnv-0.0.11.dist-info/METADATA
configAWSEnv-0.0.11.dist-info/RECORD
configAWSEnv-0.0.11.dist-info/WHEEL
configAWSEnv-0.0.11.dist-info/entry_points.txt
configAWSEnv-0.0.11.dist-info/metadata.json
configAWSEnv-0.0.11.dist-info/namespace_packages.txt
configAWSEnv-0.0.11.dist-info/top_level.txt
configAWSEnv-0.0.11.dist-info/zip-safe
